ujotypes/__init__.py
ujotypes/_ujotypes.cpython-311-x86_64-linux-gnu.so
ujotypes/tools/__init__.py
ujotypes/tools/type_conversion.py
ujotypes/tools/ujo_to_python.py
ujotypes/variants/__init__.py
ujotypes/variants/base.py
ujotypes/variants/boolean.py
ujotypes/variants/container.py
ujotypes/variants/float.py
ujotypes/variants/integer.py
ujotypes/variants/none.py
ujotypes/variants/string.py
ujotypes/variants/timestamp.py
ujotypes-0.2.134.dist-info/LICENSE
ujotypes-0.2.134.dist-info/METADATA
ujotypes-0.2.134.dist-info/WHEEL
ujotypes-0.2.134.dist-info/top_level.txt
ujotypes-0.2.134.dist-info/RECORD
