Metadata-Version: 2.1
Name: ujotypes
Version: 0.2.134
Summary: Ujo Types for PythonPython wrapper for the ujotypes-c libraray for inmemory handling of UJO container objects
Home-page: https://www.industrial-devops.org/
Author: wobe-systems GmbH
Author-email: info@industrial-devops.org
License: MIT
Project-URL: Bug Tracker, https://tracker.industrial-devops.org
Project-URL: Documentation, https://ujotypes-py.readthedocs.org/
Project-URL: Source Code, https://git.industrial-devops.org/titan/related-projects/ujotypes-py
Platform: Windows
Platform: Linux
Classifier: Programming Language :: Python :: 3
Classifier: License :: OSI Approved :: MIT License
Classifier: Operating System :: Microsoft :: Windows
Classifier: Operating System :: POSIX :: Linux
Classifier: Development Status :: 4 - Beta
Classifier: Programming Language :: Python :: 3 :: Only
Classifier: Programming Language :: Python :: 3.7
Classifier: Programming Language :: Python :: 3.8
Classifier: Programming Language :: Python :: 3.9
Classifier: Programming Language :: Python :: 3.10
Classifier: Programming Language :: Python :: 3.11
Classifier: Programming Language :: Python :: 3.12
License-File: LICENSE
